setup.py
tracwiki/__init__.py
tracwiki/tracwiki.py
tracwiki.egg-info/PKG-INFO
tracwiki.egg-info/SOURCES.txt
tracwiki.egg-info/dependency_links.txt
tracwiki.egg-info/entry_points.txt
tracwiki.egg-info/requires.txt
tracwiki.egg-info/top_level.txt