Metadata-Version: 1.1
Name: tracwiki
Version: 0.12.0
Summary: Checkout and commit trac wiki pages.
Home-page: https://www.fixedpoint.nl
Author: Jeroen F.J. Laros
Author-email: jlaros@fixedpoint.nl
License: MIT License
Keywords: trac wiki checkout commit
Platform: any
Classifier: Development Status :: 3 - Alpha
Classifier: Operating System :: OS Independent
Classifier: Programming Language :: Python
Requires: keyring
